{"timestamp": "2024-11-08T06:54:37.084136+00:00", "num_samples": 1, "processes": {"3492": {"pcpu": 0.0, "pmem": 0.0, "rss": 9306112, "vsz": 17244160, "timestamp": "2024-11-08T06:54:37.084136+00:00", "etime": "00:00", "stat": {"Rs": 1}, "cmd": "/opt/hostedtoolcache/Python/3.12.7/x64/bin/python /opt/hostedtoolcache/Python/3.12.7/x64/bin/dandisets-linkml-status --include-unpublished --dandi-instance dandi -l INFO"}}, "totals": {"pmem": 0.0, "pcpu": 0.0, "rss": 9306112, "vsz": 17244160}, "averages": {"rss": 9306112, "vsz": 17244160, "pmem": 0.0, "pcpu": 0.0, "num_samples": 1}}
{"timestamp": "2024-11-08T06:55:37.625021+00:00", "num_samples": 60, "processes": {"3492": {"pcpu": 99.0, "pmem": 4.0, "rss": 670388224, "vsz": 683573248, "timestamp": "2024-11-08T06:55:37.625021+00:00", "etime": "01:00", "stat": {"Rs": 43, "Ss": 17}, "cmd": "/opt/hostedtoolcache/Python/3.12.7/x64/bin/python /opt/hostedtoolcache/Python/3.12.7/x64/bin/dandisets-linkml-status --include-unpublished --dandi-instance dandi -l INFO"}}, "totals": {"pmem": 4.0, "pcpu": 99.0, "rss": 670388224, "vsz": 683573248}, "averages": {"rss": 386899353.59999996, "vsz": 398861585.0666667, "pmem": 2.2599999999999993, "pcpu": 62.605, "num_samples": 60}}
{"timestamp": "2024-11-08T06:56:37.130060+00:00", "num_samples": 59, "processes": {"3492": {"pcpu": 63.3, "pmem": 7.1, "rss": 1190346752, "vsz": 1623031808, "timestamp": "2024-11-08T06:56:37.130060+00:00", "etime": "02:00", "stat": {"Ss": 2, "Rs": 2, "Ssl": 18, "Rsl": 37}, "cmd": "/opt/hostedtoolcache/Python/3.12.7/x64/bin/python /opt/hostedtoolcache/Python/3.12.7/x64/bin/dandisets-linkml-status --include-unpublished --dandi-instance dandi -l INFO"}}, "totals": {"pmem": 7.1, "pcpu": 63.3, "rss": 1190346752, "vsz": 1623031808}, "averages": {"rss": 936721876.6101692, "vsz": 1339816873.220339, "pmem": 5.540677966101695, "pcpu": 62.93559322033899, "num_samples": 59}}
{"timestamp": "2024-11-08T06:57:37.644618+00:00", "num_samples": 60, "processes": {"3492": {"pcpu": 63.2, "pmem": 10.2, "rss": 1712787456, "vsz": 2149105664, "timestamp": "2024-11-08T06:57:37.644618+00:00", "etime": "03:00", "stat": {"Rsl": 41, "Ssl": 19}, "cmd": "/opt/hostedtoolcache/Python/3.12.7/x64/bin/python /opt/hostedtoolcache/Python/3.12.7/x64/bin/dandisets-linkml-status --include-unpublished --dandi-instance dandi -l INFO"}}, "totals": {"pmem": 10.2, "pcpu": 63.2, "rss": 1712787456, "vsz": 2149105664}, "averages": {"rss": 1457897062.4, "vsz": 1892658653.866666, "pmem": 8.65, "pcpu": 62.879999999999995, "num_samples": 60}}
{"timestamp": "2024-11-08T06:58:37.146110+00:00", "num_samples": 59, "processes": {"3492": {"pcpu": 63.3, "pmem": 13.4, "rss": 2256416768, "vsz": 2696339456, "timestamp": "2024-11-08T06:58:37.146110+00:00", "etime": "04:00", "stat": {"Ssl": 28, "Rsl": 31}, "cmd": "/opt/hostedtoolcache/Python/3.12.7/x64/bin/python /opt/hostedtoolcache/Python/3.12.7/x64/bin/dandisets-linkml-status --include-unpublished --dandi-instance dandi -l INFO"}}, "totals": {"pmem": 13.4, "pcpu": 63.3, "rss": 2256416768, "vsz": 2696339456}, "averages": {"rss": 1988909507.2542367, "vsz": 2427373463.8644056, "pmem": 11.818644067796612, "pcpu": 63.06949152542373, "num_samples": 59}}
{"timestamp": "2024-11-08T06:59:37.657318+00:00", "num_samples": 60, "processes": {"3492": {"pcpu": 63.2, "pmem": 16.7, "rss": 2812542976, "vsz": 3256569856, "timestamp": "2024-11-08T06:59:37.657318+00:00", "etime": "05:00", "stat": {"Rsl": 40, "Ssl": 20}, "cmd": "/opt/hostedtoolcache/Python/3.12.7/x64/bin/python /opt/hostedtoolcache/Python/3.12.7/x64/bin/dandisets-linkml-status --include-unpublished --dandi-instance dandi -l INFO"}}, "totals": {"pmem": 16.7, "pcpu": 63.2, "rss": 2812542976, "vsz": 3256569856}, "averages": {"rss": 2529694993.0666676, "vsz": 2972053913.6000004, "pmem": 15.045000000000002, "pcpu": 63.11666666666667, "num_samples": 60}}
{"timestamp": "2024-11-08T07:00:07.916270+00:00", "num_samples": 30, "processes": {"3492": {"pcpu": 65.7, "pmem": 17.1, "rss": 2881769472, "vsz": 3320279040, "timestamp": "2024-11-08T07:00:07.916270+00:00", "etime": "05:30", "stat": {"Rsl": 4, "Ssl": 3, "Rs": 23}, "cmd": "/opt/hostedtoolcache/Python/3.12.7/x64/bin/python /opt/hostedtoolcache/Python/3.12.7/x64/bin/dandisets-linkml-status --include-unpublished --dandi-instance dandi -l INFO"}}, "totals": {"pmem": 17.1, "pcpu": 65.7, "rss": 2881769472, "vsz": 3320279040}, "averages": {"rss": 2873343180.799999, "vsz": 3280209100.8000007, "pmem": 17.063333333333333, "pcpu": 64.14333333333336, "num_samples": 30}}
