{"timestamp": "2025-08-11T07:00:35.587725+00:00", "num_samples": 1, "processes": {"3703": {"pcpu": 0.0, "pmem": 0.0, "rss": 8388608, "vsz": 16375808, "timestamp": "2025-08-11T07:00:35.587725+00:00", "etime": "00:00", "stat": {"Rs": 1}, "cmd": "/opt/hostedtoolcache/Python/3.13.5/x64/bin/python /opt/hostedtoolcache/Python/3.13.5/x64/bin/dandisets-report-tools -l INFO linkml-translation --include-unpublished --dandi-instance dandi"}}, "totals": {"pmem": 0.0, "pcpu": 0.0, "rss": 8388608, "vsz": 16375808}, "averages": {"rss": 8388608, "vsz": 16375808, "pmem": 0.0, "pcpu": 0.0, "num_samples": 1}}
{"timestamp": "2025-08-11T07:01:36.037199+00:00", "num_samples": 60, "processes": {"3703": {"pcpu": 69.0, "pmem": 4.3, "rss": 729337856, "vsz": 742957056, "timestamp": "2025-08-11T07:01:36.037199+00:00", "etime": "01:01", "stat": {"Ds": 1, "Rs": 39, "Ss": 20}, "cmd": "/opt/hostedtoolcache/Python/3.13.5/x64/bin/python /opt/hostedtoolcache/Python/3.13.5/x64/bin/dandisets-report-tools -l INFO linkml-translation --include-unpublished --dandi-instance dandi"}}, "totals": {"pmem": 4.3, "pcpu": 69.0, "rss": 729337856, "vsz": 742957056}, "averages": {"rss": 404226184.5333334, "vsz": 416225621.3333334, "pmem": 2.356666666666667, "pcpu": 56.83333333333332, "num_samples": 60}}
{"timestamp": "2025-08-11T07:02:36.490473+00:00", "num_samples": 60, "processes": {"3703": {"pcpu": 63.1, "pmem": 7.4, "rss": 1255874560, "vsz": 1691021312, "timestamp": "2025-08-11T07:02:36.490473+00:00", "etime": "02:01", "stat": {"Ss": 3, "Rs": 3, "Ssl": 22, "Rsl": 32}, "cmd": "/opt/hostedtoolcache/Python/3.13.5/x64/bin/python /opt/hostedtoolcache/Python/3.13.5/x64/bin/dandisets-report-tools -l INFO linkml-translation --include-unpublished --dandi-instance dandi"}}, "totals": {"pmem": 7.4, "pcpu": 63.1, "rss": 1255874560, "vsz": 1691021312}, "averages": {"rss": 1000667340.8000004, "vsz": 1392683212.8000004, "pmem": 5.915000000000001, "pcpu": 61.58166666666666, "num_samples": 60}}
{"timestamp": "2025-08-11T07:03:35.934398+00:00", "num_samples": 59, "processes": {"3703": {"pcpu": 61.0, "pmem": 9.1, "rss": 1532829696, "vsz": 1969856512, "timestamp": "2025-08-11T07:03:35.934398+00:00", "etime": "03:01", "stat": {"Ssl": 42, "Rsl": 17}, "cmd": "/opt/hostedtoolcache/Python/3.13.5/x64/bin/python /opt/hostedtoolcache/Python/3.13.5/x64/bin/dandisets-report-tools -l INFO linkml-translation --include-unpublished --dandi-instance dandi"}}, "totals": {"pmem": 9.1, "pcpu": 61.0, "rss": 1532829696, "vsz": 1969856512}, "averages": {"rss": 1415633555.5254235, "vsz": 1852159271.050847, "pmem": 8.388135593220339, "pcpu": 55.852542372881345, "num_samples": 59}}
{"timestamp": "2025-08-11T07:04:36.382033+00:00", "num_samples": 60, "processes": {"3703": {"pcpu": 51.0, "pmem": 10.7, "rss": 1801564160, "vsz": 2241138688, "timestamp": "2025-08-11T07:04:36.382033+00:00", "etime": "04:01", "stat": {"Ssl": 41, "Rsl": 19}, "cmd": "/opt/hostedtoolcache/Python/3.13.5/x64/bin/python /opt/hostedtoolcache/Python/3.13.5/x64/bin/dandisets-report-tools -l INFO linkml-translation --include-unpublished --dandi-instance dandi"}}, "totals": {"pmem": 10.7, "pcpu": 51.0, "rss": 1801564160, "vsz": 2241138688}, "averages": {"rss": 1648903509.3333333, "vsz": 2087078365.866667, "pmem": 9.775000000000002, "pcpu": 47.22999999999999, "num_samples": 60}}
{"timestamp": "2025-08-11T07:05:35.824421+00:00", "num_samples": 59, "processes": {"3703": {"pcpu": 46.2, "pmem": 12.8, "rss": 2148429824, "vsz": 2589978624, "timestamp": "2025-08-11T07:05:35.824421+00:00", "etime": "05:01", "stat": {"Rsl": 22, "Ssl": 37}, "cmd": "/opt/hostedtoolcache/Python/3.13.5/x64/bin/python /opt/hostedtoolcache/Python/3.13.5/x64/bin/dandisets-report-tools -l INFO linkml-translation --include-unpublished --dandi-instance dandi"}}, "totals": {"pmem": 12.8, "pcpu": 46.2, "rss": 2148429824, "vsz": 2589978624}, "averages": {"rss": 1999352641.0847456, "vsz": 2440221713.355932, "pmem": 11.86779661016949, "pcpu": 45.30000000000001, "num_samples": 59}}
{"timestamp": "2025-08-11T07:06:36.276075+00:00", "num_samples": 60, "processes": {"3703": {"pcpu": 43.8, "pmem": 14.7, "rss": 2473500672, "vsz": 2917531648, "timestamp": "2025-08-11T07:06:36.276075+00:00", "etime": "06:01", "stat": {"Ssl": 39, "Rsl": 21}, "cmd": "/opt/hostedtoolcache/Python/3.13.5/x64/bin/python /opt/hostedtoolcache/Python/3.13.5/x64/bin/dandisets-report-tools -l INFO linkml-translation --include-unpublished --dandi-instance dandi"}}, "totals": {"pmem": 14.7, "pcpu": 43.8, "rss": 2473500672, "vsz": 2917531648}, "averages": {"rss": 2295024298.666667, "vsz": 2738145348.2666664, "pmem": 13.638333333333335, "pcpu": 42.89166666666666, "num_samples": 60}}
{"timestamp": "2025-08-11T07:07:35.728215+00:00", "num_samples": 59, "processes": {"3703": {"pcpu": 45.3, "pmem": 18.0, "rss": 3030994944, "vsz": 3479703552, "timestamp": "2025-08-11T07:07:35.728215+00:00", "etime": "07:00", "stat": {"Rsl": 36, "Ssl": 23}, "cmd": "/opt/hostedtoolcache/Python/3.13.5/x64/bin/python /opt/hostedtoolcache/Python/3.13.5/x64/bin/dandisets-report-tools -l INFO linkml-translation --include-unpublished --dandi-instance dandi"}}, "totals": {"pmem": 18.0, "pcpu": 45.3, "rss": 3030994944, "vsz": 3479703552}, "averages": {"rss": 2746910893.5593224, "vsz": 3193545328.8135586, "pmem": 16.3271186440678, "pcpu": 43.903389830508466, "num_samples": 59}}
{"timestamp": "2025-08-11T07:08:36.182941+00:00", "num_samples": 60, "processes": {"3703": {"pcpu": 47.7, "pmem": 21.5, "rss": 3614396416, "vsz": 4062732288, "timestamp": "2025-08-11T07:08:36.182941+00:00", "etime": "08:01", "stat": {"Ssl": 22, "Rsl": 38}, "cmd": "/opt/hostedtoolcache/Python/3.13.5/x64/bin/python /opt/hostedtoolcache/Python/3.13.5/x64/bin/dandisets-report-tools -l INFO linkml-translation --include-unpublished --dandi-instance dandi"}}, "totals": {"pmem": 21.5, "pcpu": 47.7, "rss": 3614396416, "vsz": 4062732288}, "averages": {"rss": 3327403349.333333, "vsz": 3776344268.799999, "pmem": 19.785000000000004, "pcpu": 46.444999999999986, "num_samples": 60}}
{"timestamp": "2025-08-11T07:09:35.628444+00:00", "num_samples": 59, "processes": {"3703": {"pcpu": 50.6, "pmem": 25.4, "rss": 4260421632, "vsz": 4711546880, "timestamp": "2025-08-11T07:09:35.628444+00:00", "etime": "09:00", "stat": {"Rsl": 41, "Ssl": 18}, "cmd": "/opt/hostedtoolcache/Python/3.13.5/x64/bin/python /opt/hostedtoolcache/Python/3.13.5/x64/bin/dandisets-report-tools -l INFO linkml-translation --include-unpublished --dandi-instance dandi"}}, "totals": {"pmem": 25.4, "pcpu": 50.6, "rss": 4260421632, "vsz": 4711546880}, "averages": {"rss": 3952910960.8135586, "vsz": 4402475424.542375, "pmem": 23.51694915254237, "pcpu": 49.159322033898306, "num_samples": 59}}
{"timestamp": "2025-08-11T07:10:08.880165+00:00", "num_samples": 33, "processes": {"3703": {"pcpu": 53.2, "pmem": 25.7, "rss": 4315340800, "vsz": 4762038272, "timestamp": "2025-08-11T07:10:08.880165+00:00", "etime": "09:34", "stat": {"Rsl": 4, "Rs": 29}, "cmd": "/opt/hostedtoolcache/Python/3.13.5/x64/bin/python /opt/hostedtoolcache/Python/3.13.5/x64/bin/dandisets-report-tools -l INFO linkml-translation --include-unpublished --dandi-instance dandi"}}, "totals": {"pmem": 25.7, "pcpu": 53.2, "rss": 4315340800, "vsz": 4762038272}, "averages": {"rss": 4311551503.515151, "vsz": 4719496098.909091, "pmem": 25.67272727272727, "pcpu": 51.88484848484848, "num_samples": 33}}
