{"command": "dandisets-report-tools -l INFO linkml-translation --include-unpublished --dandi-instance dandi", "system": {"cpu_total": 4, "memory_total": 16773005312, "hostname": "pkrvmb0rtv228un", "uid": 1001, "user": "runner"}, "env": {}, "gpu": null, "duct_version": "0.15.0", "schema_version": "0.2.2", "execution_summary": {"exit_code": 0, "command": "dandisets-report-tools -l INFO linkml-translation --include-unpublished --dandi-instance dandi", "logs_prefix": ".duct/logs/2025.08.27T06.56.17-3665_", "wall_clock_time": 404.5116693973541, "peak_rss": 4419346432, "average_rss": 2393964258.7064657, "peak_vsz": 4866650112, "average_vsz": 2761661934.1691546, "peak_pmem": 26.3, "average_pmem": 14.21990049751245, "peak_pcpu": 75.9, "average_pcpu": 69.73308457711445, "num_samples": 402, "num_reports": 8, "start_time": 1756277777.6354601, "end_time": 1756278182.1471295, "working_directory": "/home/runner/work/dandisets-linkml-status/dandisets-linkml-status"}, "output_paths": {"stdout": ".duct/logs/2025.08.27T06.56.17-3665_stdout", "stderr": ".duct/logs/2025.08.27T06.56.17-3665_stderr", "usage": ".duct/logs/2025.08.27T06.56.17-3665_usage.json", "info": ".duct/logs/2025.08.27T06.56.17-3665_info.json", "prefix": ".duct/logs/2025.08.27T06.56.17-3665_"}, "working_directory": "/home/runner/work/dandisets-linkml-status/dandisets-linkml-status", "message": ""}