{"command": "dandisets-report-tools -l INFO linkml-translation --include-unpublished --dandi-instance dandi", "system": {"cpu_total": 4, "memory_total": 16771854336, "hostname": "runnervmfg25i", "uid": 1001, "user": "runner"}, "env": {}, "gpu": null, "duct_version": "0.17.0", "schema_version": "0.2.2", "execution_summary": {"exit_code": 0, "command": "dandisets-report-tools -l INFO linkml-translation --include-unpublished --dandi-instance dandi", "logs_prefix": ".duct/logs/2025.11.10T06.57.43-3786_", "wall_clock_time": 507.3486421108246, "peak_rss": 4186755072, "average_rss": 2211863554.0277224, "peak_vsz": 4632940544, "average_vsz": 2583560378.550497, "peak_pmem": 24.9, "average_pmem": 13.138019801980198, "peak_pcpu": 64.0, "average_pcpu": 48.47049504950496, "num_samples": 505, "num_reports": 10, "start_time": 1762757863.3202696, "end_time": 1762758370.6689117, "working_directory": "/home/runner/work/dandisets-linkml-status/dandisets-linkml-status"}, "output_paths": {"stdout": ".duct/logs/2025.11.10T06.57.43-3786_stdout", "stderr": ".duct/logs/2025.11.10T06.57.43-3786_stderr", "usage": ".duct/logs/2025.11.10T06.57.43-3786_usage.json", "info": ".duct/logs/2025.11.10T06.57.43-3786_info.json", "prefix": ".duct/logs/2025.11.10T06.57.43-3786_"}, "working_directory": "/home/runner/work/dandisets-linkml-status/dandisets-linkml-status", "message": ""}