{"timestamp": "2025-10-22T06:57:15.721370+00:00", "num_samples": 1, "processes": {"3678": {"pcpu": 0.0, "pmem": 0.0, "rss": 8388608, "vsz": 16392192, "timestamp": "2025-10-22T06:57:15.721370+00:00", "etime": "00:00", "stat": {"Rs": 1}, "cmd": "/opt/hostedtoolcache/Python/3.13.8/x64/bin/python /opt/hostedtoolcache/Python/3.13.8/x64/bin/dandisets-report-tools -l INFO linkml-translation --include-unpublished --dandi-instance dandi"}}, "totals": {"pmem": 0.0, "pcpu": 0.0, "rss": 8388608, "vsz": 16392192}, "averages": {"rss": 8388608, "vsz": 16392192, "pmem": 0.0, "pcpu": 0.0, "num_samples": 1}}
{"timestamp": "2025-10-22T06:58:16.177473+00:00", "num_samples": 60, "processes": {"3678": {"pcpu": 68.0, "pmem": 3.4, "rss": 580395008, "vsz": 592228352, "timestamp": "2025-10-22T06:58:16.177473+00:00", "etime": "01:00", "stat": {"Ds": 1, "Ss": 30, "Rs": 29}, "cmd": "/opt/hostedtoolcache/Python/3.13.8/x64/bin/python /opt/hostedtoolcache/Python/3.13.8/x64/bin/dandisets-report-tools -l INFO linkml-translation --include-unpublished --dandi-instance dandi"}}, "totals": {"pmem": 3.4, "pcpu": 68.0, "rss": 580395008, "vsz": 592228352}, "averages": {"rss": 312291601.0666667, "vsz": 323342472.53333336, "pmem": 1.8150000000000002, "pcpu": 38.720000000000006, "num_samples": 60}}
{"timestamp": "2025-10-22T06:59:16.636510+00:00", "num_samples": 60, "processes": {"3678": {"pcpu": 50.9, "pmem": 6.7, "rss": 1131634688, "vsz": 1560137728, "timestamp": "2025-10-22T06:59:16.636510+00:00", "etime": "02:01", "stat": {"Ss": 9, "Rs": 12, "Ssl": 20, "Rsl": 19}, "cmd": "/opt/hostedtoolcache/Python/3.13.8/x64/bin/python /opt/hostedtoolcache/Python/3.13.8/x64/bin/dandisets-report-tools -l INFO linkml-translation --include-unpublished --dandi-instance dandi"}}, "totals": {"pmem": 6.7, "pcpu": 50.9, "rss": 1131634688, "vsz": 1560137728}, "averages": {"rss": 861669444.2666669, "vsz": 1144760456.533333, "pmem": 5.091666666666667, "pcpu": 48.86000000000001, "num_samples": 60}}
{"timestamp": "2025-10-22T07:00:16.087306+00:00", "num_samples": 59, "processes": {"3678": {"pcpu": 52.4, "pmem": 9.7, "rss": 1637122048, "vsz": 2069348352, "timestamp": "2025-10-22T07:00:16.087306+00:00", "etime": "03:00", "stat": {"Ssl": 30, "Rsl": 29}, "cmd": "/opt/hostedtoolcache/Python/3.13.8/x64/bin/python /opt/hostedtoolcache/Python/3.13.8/x64/bin/dandisets-report-tools -l INFO linkml-translation --include-unpublished --dandi-instance dandi"}}, "totals": {"pmem": 9.7, "pcpu": 52.4, "rss": 1637122048, "vsz": 2069348352}, "averages": {"rss": 1391070468.338983, "vsz": 1821854633.2203386, "pmem": 8.249152542372881, "pcpu": 51.6677966101695, "num_samples": 59}}
{"timestamp": "2025-10-22T07:01:16.533622+00:00", "num_samples": 60, "processes": {"3678": {"pcpu": 52.7, "pmem": 12.9, "rss": 2166767616, "vsz": 2602807296, "timestamp": "2025-10-22T07:01:16.533622+00:00", "etime": "04:01", "stat": {"Ssl": 26, "Rsl": 34}, "cmd": "/opt/hostedtoolcache/Python/3.13.8/x64/bin/python /opt/hostedtoolcache/Python/3.13.8/x64/bin/dandisets-report-tools -l INFO linkml-translation --include-unpublished --dandi-instance dandi"}}, "totals": {"pmem": 12.9, "pcpu": 52.7, "rss": 2166767616, "vsz": 2602807296}, "averages": {"rss": 1903463082.6666667, "vsz": 2338137361.0666666, "pmem": 11.3, "pcpu": 52.209999999999994, "num_samples": 60}}
{"timestamp": "2025-10-22T07:02:15.968207+00:00", "num_samples": 59, "processes": {"3678": {"pcpu": 53.0, "pmem": 16.1, "rss": 2711740416, "vsz": 3153022976, "timestamp": "2025-10-22T07:02:15.968207+00:00", "etime": "05:00", "stat": {"Ssl": 24, "Rsl": 35}, "cmd": "/opt/hostedtoolcache/Python/3.13.8/x64/bin/python /opt/hostedtoolcache/Python/3.13.8/x64/bin/dandisets-report-tools -l INFO linkml-translation --include-unpublished --dandi-instance dandi"}}, "totals": {"pmem": 16.1, "pcpu": 53.0, "rss": 2711740416, "vsz": 3153022976}, "averages": {"rss": 2439312401.3559318, "vsz": 2878100913.8983054, "pmem": 14.491525423728813, "pcpu": 52.805084745762706, "num_samples": 59}}
{"timestamp": "2025-10-22T07:03:16.410970+00:00", "num_samples": 60, "processes": {"3678": {"pcpu": 53.6, "pmem": 19.5, "rss": 3271786496, "vsz": 3715211264, "timestamp": "2025-10-22T07:03:16.410970+00:00", "etime": "06:01", "stat": {"Rsl": 33, "Ssl": 27}, "cmd": "/opt/hostedtoolcache/Python/3.13.8/x64/bin/python /opt/hostedtoolcache/Python/3.13.8/x64/bin/dandisets-report-tools -l INFO linkml-translation --include-unpublished --dandi-instance dandi"}}, "totals": {"pmem": 19.5, "pcpu": 53.6, "rss": 3271786496, "vsz": 3715211264}, "averages": {"rss": 2988318105.6, "vsz": 3430968115.1999993, "pmem": 17.771666666666665, "pcpu": 53.46500000000001, "num_samples": 60}}
{"timestamp": "2025-10-22T07:04:15.849578+00:00", "num_samples": 59, "processes": {"3678": {"pcpu": 54.1, "pmem": 22.6, "rss": 3805773824, "vsz": 4249227264, "timestamp": "2025-10-22T07:04:15.849578+00:00", "etime": "07:00", "stat": {"Rsl": 37, "Ssl": 22}, "cmd": "/opt/hostedtoolcache/Python/3.13.8/x64/bin/python /opt/hostedtoolcache/Python/3.13.8/x64/bin/dandisets-report-tools -l INFO linkml-translation --include-unpublished --dandi-instance dandi"}}, "totals": {"pmem": 22.6, "pcpu": 54.1, "rss": 3805773824, "vsz": 4249227264}, "averages": {"rss": 3535099036.2033896, "vsz": 3978526442.305084, "pmem": 21.022033898305093, "pcpu": 53.898305084745765, "num_samples": 59}}
{"timestamp": "2025-10-22T07:05:16.291039+00:00", "num_samples": 60, "processes": {"3678": {"pcpu": 54.6, "pmem": 25.9, "rss": 4348223488, "vsz": 4794949632, "timestamp": "2025-10-22T07:05:16.291039+00:00", "etime": "08:01", "stat": {"Ssl": 22, "Rsl": 38}, "cmd": "/opt/hostedtoolcache/Python/3.13.8/x64/bin/python /opt/hostedtoolcache/Python/3.13.8/x64/bin/dandisets-report-tools -l INFO linkml-translation --include-unpublished --dandi-instance dandi"}}, "totals": {"pmem": 25.9, "pcpu": 54.6, "rss": 4348223488, "vsz": 4794949632}, "averages": {"rss": 4087562103.4666657, "vsz": 4532202291.200001, "pmem": 24.323333333333334, "pcpu": 54.315, "num_samples": 60}}
{"timestamp": "2025-10-22T07:06:09.685821+00:00", "num_samples": 53, "processes": {"3678": {"pcpu": 57.0, "pmem": 27.3, "rss": 4586717184, "vsz": 5033615360, "timestamp": "2025-10-22T07:06:09.685821+00:00", "etime": "08:54", "stat": {"Rsl": 13, "Ssl": 11, "Rs": 29}, "cmd": "/opt/hostedtoolcache/Python/3.13.8/x64/bin/python /opt/hostedtoolcache/Python/3.13.8/x64/bin/dandisets-report-tools -l INFO linkml-translation --include-unpublished --dandi-instance dandi"}}, "totals": {"pmem": 27.3, "pcpu": 57.0, "rss": 4586717184, "vsz": 5033615360}, "averages": {"rss": 4533676302.490567, "vsz": 4954040667.773585, "pmem": 26.981132075471695, "pcpu": 55.207547169811335, "num_samples": 53}}
