{
  "id": "DANDI:001283/draft",
  "url": "https://dandiarchive.org/dandiset/001283/draft",
  "name": "Is there a ubiquitous spectrolaminar motif of local field potential power across the primate neocortex?",
  "access": [
    {
      "status": "dandi:OpenAccess",
      "schemaKey": "AccessRequirements"
    }
  ],
  "license": [
    "spdx:CC-BY-4.0"
  ],
  "version": "draft",
  "citation": "Mackey, Chase (2024) Is there a ubiquitous spectrolaminar motif of local field potential power across the primate neocortex? (Version draft) [Data set]. DANDI Archive. https://dandiarchive.org/dandiset/001283/draft",
  "schemaKey": "Dandiset",
  "identifier": "DANDI:001283",
  "repository": "https://dandiarchive.org",
  "contributor": [
    {
      "name": "Mackey, Chase",
      "email": "seemackey@gmail.com",
      "roleName": [
        "dcite:ContactPerson"
      ],
      "schemaKey": "Person",
      "affiliation": [],
      "includeInCitation": true
    }
  ],
  "dateCreated": "2024-12-23T15:48:29.477270+00:00",
  "description": "This is a dataset accompanying the preprint by Mackey et al. (2024) under the same title (\"Is there a ubiquitous [...]\"); DOI: 10.1101/2024.09.18.613490. See the README for details about the format of the data. ",
  "assetsSummary": {
    "schemaKey": "AssetsSummary",
    "numberOfBytes": 0,
    "numberOfFiles": 0
  },
  "schemaVersion": "0.6.8",
  "manifestLocation": [
    "https://api.dandiarchive.org/api/dandisets/001283/versions/draft/assets/"
  ]
}