{
  "id": "DANDI:000213/draft",
  "url": "https://dandiarchive.org/dandiset/000213/draft",
  "name": "Transformation of a Spatial Map across the Hippocampal-Lateral Septal Circuit",
  "about": [
    {
      "name": "hippocampal formation",
      "schemaKey": "Anatomy",
      "identifier": "http://purl.obolibrary.org/obo/UBERON_0002421"
    },
    {
      "name": "Lateral Septum Complex",
      "schemaKey": "Anatomy",
      "identifier": "http://purl.obolibrary.org/obo/UBERON_0007628"
    }
  ],
  "access": [
    {
      "status": "dandi:OpenAccess",
      "schemaKey": "AccessRequirements"
    }
  ],
  "license": [
    "spdx:CC-BY-4.0"
  ],
  "version": "draft",
  "citation": "Tingley, David; Buzs\u00e1ki, Gy\u00f6rgy (2025) Transformation of a Spatial Map across the Hippocampal-Lateral Septal Circuit (Version draft) [Data set]. DANDI Archive. https://dandiarchive.org/dandiset/000213/draft",
  "keywords": [
    "hippocampus",
    "lateral septum",
    "electrophysiology"
  ],
  "schemaKey": "Dandiset",
  "identifier": "DANDI:000213",
  "repository": "https://dandiarchive.org",
  "contributor": [
    {
      "name": "Tingley, David",
      "email": "dtingley@bidmc.harvard.edu",
      "roleName": [
        "dcite:ContactPerson",
        "dcite:Author",
        "dcite:DataCollector"
      ],
      "schemaKey": "Person",
      "identifier": "0000-0003-4263-0476",
      "affiliation": [
        {
          "name": "New York University Langone Medical Center",
          "schemaKey": "Affiliation",
          "identifier": "https://ror.org/005dvqh91"
        },
        {
          "name": "New York University",
          "schemaKey": "Affiliation",
          "identifier": "https://ror.org/0190ak572"
        }
      ],
      "includeInCitation": true
    },
    {
      "name": "Buzs\u00e1ki, Gy\u00f6rgy",
      "roleName": [
        "dcite:Author"
      ],
      "schemaKey": "Person",
      "identifier": "0000-0002-3100-4800",
      "affiliation": [
        {
          "name": "New York University Langone Medical Center",
          "schemaKey": "Affiliation",
          "identifier": "https://ror.org/005dvqh91"
        },
        {
          "name": "New York University",
          "schemaKey": "Affiliation",
          "identifier": "https://ror.org/0190ak572"
        }
      ],
      "includeInCitation": true
    },
    {
      "url": "https://www.nih.gov/",
      "name": "National Institutes of Health",
      "roleName": [
        "dcite:Funder"
      ],
      "schemaKey": "Organization",
      "identifier": "https://ror.org/01cwqze88",
      "awardNumber": " MH54671, MH107396, and NS 090583",
      "contactPoint": [],
      "includeInCitation": false
    },
    {
      "url": "https://www.nsf.gov/",
      "name": "National Science Foundation",
      "roleName": [
        "dcite:Funder"
      ],
      "schemaKey": "Organization",
      "identifier": "https://ror.org/021nxhr62",
      "awardNumber": "NSF PIRE grant (#1545858)",
      "contactPoint": [],
      "includeInCitation": false
    },
    {
      "url": "http://www.thesimonsfoundation.ca/",
      "name": "Simons Foundation",
      "roleName": [
        "dcite:Funder"
      ],
      "schemaKey": "Organization",
      "identifier": "https://ror.org/01cmst727",
      "awardNumber": "351109",
      "contactPoint": [],
      "includeInCitation": false
    },
    {
      "name": "Baker, Cody",
      "roleName": [
        "dcite:DataCurator"
      ],
      "schemaKey": "Person",
      "identifier": "0000-0002-0829-4790"
    }
  ],
  "dateCreated": "2022-01-11T21:16:19.103724+00:00",
  "description": "The hippocampus constructs a map of the environment. How this \u201ccognitive map\u201d is utilized by other brain regions to guide behavior remains unexplored. To examine how neuronal firing patterns in the hippocampus are transmitted and transformed, we recorded neurons in its principal subcortical target, the lateral septum (LS). We observed that LS neurons carry reliable spatial information in the phase of action potentials, relative to hippocampal theta oscillations, while the firing rates of LS neurons remained uninformative. Furthermore, this spatial phase code had an anatomical microstructure within the LS and was bound to the hippocampal spatial code by synchronous gamma frequency cell assemblies. Using a data-driven model, we show that rate-independent spatial tuning arises through the dynamic weighting of CA1 and CA3 cell assemblies. Our findings demonstrate that transformation of the hippocampal spatial map depends on higher-order theta-dependent neuronal sequences.",
  "publishedBy": {
    "id": "urn:uuid:49ad30cf-f353-4635-95c2-d2b76eff84fb",
    "name": "DANDI publish",
    "endDate": "2025-06-24T04:38:15.843806+00:00",
    "schemaKey": "PublishActivity",
    "startDate": "2025-06-24T04:38:15.843806+00:00",
    "wasAssociatedWith": [
      {
        "id": "urn:uuid:5494e9dd-5a36-434b-bd81-68fc262a2d91",
        "name": "DANDI API",
        "version": "0.1.0",
        "schemaKey": "Software",
        "identifier": "RRID:SCR_017571"
      }
    ]
  },
  "assetsSummary": {
    "species": [
      {
        "name": "Rattus norvegicus - Norway rat",
        "schemaKey": "SpeciesType",
        "identifier": "http://purl.obolibrary.org/obo/NCBITaxon_10116"
      }
    ],
    "approach": [
      {
        "name": "electrophysiological approach",
        "schemaKey": "ApproachType"
      },
      {
        "name": "behavioral approach",
        "schemaKey": "ApproachType"
      }
    ],
    "schemaKey": "AssetsSummary",
    "dataStandard": [
      {
        "name": "Neurodata Without Borders (NWB)",
        "schemaKey": "StandardsType",
        "identifier": "RRID:SCR_015242"
      }
    ],
    "numberOfBytes": 1527009268863,
    "numberOfFiles": 67,
    "numberOfSubjects": 5,
    "variableMeasured": [
      "Position",
      "CompassDirection",
      "ElectricalSeries",
      "LFP",
      "Units",
      "SpatialSeries"
    ],
    "measurementTechnique": [
      {
        "name": "multi electrode extracellular electrophysiology recording technique",
        "schemaKey": "MeasurementTechniqueType"
      },
      {
        "name": "spike sorting technique",
        "schemaKey": "MeasurementTechniqueType"
      },
      {
        "name": "behavioral technique",
        "schemaKey": "MeasurementTechniqueType"
      },
      {
        "name": "signal filtering technique",
        "schemaKey": "MeasurementTechniqueType"
      }
    ]
  },
  "datePublished": "2025-06-24T04:38:15.843806+00:00",
  "schemaVersion": "0.6.0",
  "ethicsApproval": [],
  "wasGeneratedBy": [],
  "relatedResource": [
    {
      "url": "https://doi.org/10.1016/j.neuron.2018.04.028",
      "name": "Transformation of a Spatial Map across the Hippocampal-Lateral Septal Circuit",
      "relation": "dcite:IsDescribedBy",
      "schemaKey": "Resource",
      "identifier": "https://doi.org/10.1016/j.neuron.2018.04.028",
      "repository": "Neuron",
      "resourceType": "dcite:JournalArticle"
    }
  ],
  "manifestLocation": [
    "https://api.dandiarchive.org/api/dandisets/000213/versions/draft/assets/"
  ]
}